garlic/__init__.py
garlic/env.py
garlic/execute.py
garlic/formatting.py
garlic/llms.py
garlic/py.typed
garlic/special.py
paradigm_garlic-0.2.6.dist-info/WHEEL
paradigm_garlic-0.2.6.dist-info/METADATA
paradigm_garlic-0.2.6.dist-info/RECORD
