Metadata-Version: 2.4
Name: paradigm_garlic
Version: 0.2.6
Summary: garlic is a cli and python interface for Allium data
Requires-Python: >=3.9
Classifier: Development Status :: 4 - Beta
Classifier: Intended Audience :: Developers
Classifier: Intended Audience :: Financial and Insurance Industry
Classifier: Intended Audience :: Science/Research
Classifier: License :: OSI Approved :: Apache Software License
Classifier: License :: OSI Approved :: MIT License
Classifier: Natural Language :: English
Classifier: Operating System :: MacOS
Classifier: Operating System :: Microsoft :: Windows
Classifier: Operating System :: POSIX :: Linux
Classifier: Programming Language :: Python :: 3.7
Classifier: Programming Language :: Python :: 3.8
Classifier: Programming Language :: Python :: 3.9
Classifier: Programming Language :: Python :: 3.10
Classifier: Programming Language :: Python :: 3.11
Classifier: Programming Language :: Python :: 3.12
Classifier: Typing :: Typed
Requires-Dist: pandas>=2.3.1
Requires-Dist: polars >= 1.0
Requires-Dist: pyarrow<19.0.0
Requires-Dist: snowflake-connector-python >= 3.15.0
Requires-Dist: tooltime>=0.3.4
Requires-Dist: typing-extensions >=4.9.0 ; extra == "test"
Project-URL: Documentation, https://github.com/paradigmxyz/garlic
Project-URL: Source, https://github.com/paradigmxyz/garlic
Provides-Extra: test
